odoo/addons/ssi_master_data_mixin/README.rst
odoo/addons/ssi_master_data_mixin/__init__.py
odoo/addons/ssi_master_data_mixin/__manifest__.py
odoo/addons/ssi_master_data_mixin/models/__init__.py
odoo/addons/ssi_master_data_mixin/models/mixin_master_data.py
odoo/addons/ssi_master_data_mixin/static/description/icon.png
odoo/addons/ssi_master_data_mixin/views/mixin_master_data_views.xml
odoo14_addon_ssi_master_data_mixin-14.0.4.3.0.dist-info/METADATA
odoo14_addon_ssi_master_data_mixin-14.0.4.3.0.dist-info/WHEEL
odoo14_addon_ssi_master_data_mixin-14.0.4.3.0.dist-info/top_level.txt
odoo14_addon_ssi_master_data_mixin-14.0.4.3.0.dist-info/RECORD
